Workbook

Sheet Raw Data 
G1: RAW DATA FOR RELIANCE LTD.
B3: From P&L Statement Extract : (₹ Crores)
B5: Particulars | C5: FY2022-23 | D5: FY2023-24 | E5: FY2024-25
B6: Revenue from Operations | C6: 891311 | D6: 914472 | E6: 980136
B7: Cost of Goods Sold | C7: 588483 | D7: 585343 | E7: 629689
B8: Gross Profit | C8: 302828 | D8: 329129 | E8: 350447
B9: Operating Expenses | C9: 749149 | D9: 752290 | E9: 814692
B10: EBITDA | C10: 153920 | D10: 178290 | E10: 165421
B11: Depreciation | C11: 40303 | D11: 50832 | E11: 53136
B12: EBIT | C12: 113167 | D12: 127458 | E12: 130286
B13: Interest/Finance Cost | C13: 19571 | D13: 23118 | E13: 24269
B14: Profit Before Tax (PBT) | C14: 94046 | D14: 104340 | E14: 106017
B15: Tax | C15: 20376 | D15: 25707 | E15: 25230
B16: Net Profit (PAT) | C16: 74088 | D16: 79020 | E16: 81309
B19: From Balance Sheet extract: | E19: (₹ Crores)
B21: Particulars | C21: FY2022-23 | D21: FY2023-24 | E21: FY2024-25
B22: Current Assets | C22: 425296 | D22: 470100 | E22: 499270
B23: Current Liabilities | C23: 395743 | D23: 397367 | E23: 453737
B24: Inventory | C24: 140008 | D24: 119502 | E24: 118709
B25: Trade Receivables | C25: 28448 | D25: 31628 | E25: 42121
B26: Cash & Cash Equivalents | C26: 68664 | D26: 97225 | E26: 106502
B27: Total Assets | C27: 1607431 | D27: 1755986 | E27: 1950121
B28: Total Equity | C28: 828881 | D28: 925788 | E28: 1009626
B29: Total Debt | C29: 313966 | D29: 324622 | E29: 347530
B30: Total Liabilities | C30: 778558 | D30: 830198 | E30: 940495

Sheet Ratio Analysis
H1: Ratio Analysis
B3: Ratio Analysis sheet
B5: Ratios | C5: FY2023 | D5: FY2024 | E5: FY2025 | F5: Benchmark
B6: Profitability Ratios
B7: GP Margin % | C7: =('Raw Data '!C8/'Raw Data '!C6)*100 -> 33.975571 | D7: =('Raw Data '!D8/'Raw Data '!D6)*100 -> 35.991151 | E7: =('Raw Data '!E8/'Raw Data '!E6)*100 -> 35.754936 | F7: Higher the better
B8: Net Profit Margin % | C8: =('Raw Data '!C16/'Raw Data '!C6)*100 -> 8.3122502 | D8: =('Raw Data '!D16/'Raw Data '!D6)*100 -> 8.6410519 | E8: =('Raw Data '!E16/'Raw Data '!E6)*100 -> 8.2956855 | F8: Higher the better
B9: EBITDA Margin % | C9: ='Raw Data '!C10/'Raw Data '!C6*100 -> 17.268944 | D9: ='Raw Data '!D10/'Raw Data '!D6*100 -> 19.496496 | E9: ='Raw Data '!E10/'Raw Data '!E6*100 -> 16.877352 | F9: Higher the better
B10: ROE % | C10: ='Raw Data '!C16/'Raw Data '!C28*100 -> 8.9383156 | D10: ='Raw Data '!D16/'Raw Data '!D28*100 -> 8.5354314 | E10: ='Raw Data '!E16/'Raw Data '!E28*100 -> 8.0533782 | F10: Above 15% is good
B11: ROA % | C11: ='Raw Data '!C16/'Raw Data '!C27*100 -> 4.6090936 | D11: ='Raw Data '!D16/'Raw Data '!D27*100 -> 4.5000359 | E11: ='Raw Data '!E16/'Raw Data '!E27*100 -> 4.1694336 | F11: Above 5% is good
B13: Liquidity Ratios
B14: Current Ratio | C14: ='Raw Data '!C22/'Raw Data '!C23 -> 1.0746773 | D14: ='Raw Data '!D22/'Raw Data '!D23 -> 1.1830373 | E14: ='Raw Data '!E22/'Raw Data '!E23 -> 1.1003511 | F14: 2:1 is ideal
B15: Quick Ratio | C15: =('Raw Data '!C22-'Raw Data '!C24)/'Raw Data '!C23 -> 0.72089209 | D15: =('Raw Data '!D22-'Raw Data '!D24)/'Raw Data '!D23 -> 0.88230276 | E15: =('Raw Data '!E22-'Raw Data '!E24)/'Raw Data '!E23 -> 0.83872596 | F15: 1:1 is ideal
B17: Solvency Ratios
B18: Debt to Equity | C18: ='Raw Data '!C29/'Raw Data '!C28 -> 0.37878296 | D18: ='Raw Data '!D29/'Raw Data '!D28 -> 0.35064399 | E18: ='Raw Data '!E29/'Raw Data '!E28 -> 0.34421657 | F18: Lower the better
B19: Interest Coverage | C19: ='Raw Data '!C12/'Raw Data '!C13 -> 5.7823821 | D19: ='Raw Data '!D12/'Raw Data '!D13 -> 5.5133662 | E19: ='Raw Data '!E12/'Raw Data '!E13 -> 5.3684124 | F19: Above 3x is good
B21: Efficiency Ratio
B22: Asset Turnover | C22: ='Raw Data '!C6/'Raw Data '!C27 -> 0.5544941 | D22: ='Raw Data '!D6/'Raw Data '!D27 -> 0.52077408 | E22: ='Raw Data '!E6/'Raw Data '!E27 -> 0.50260266 | F22: Higher the better

Sheet Dashboard
G1: Reliance Industries Ltd. — Financial Analysis Dashboard (FY2023-25)
B2: Chart 1: Revenue vs Net Profit
B3: FY2023 | C3: FY2024 | D3: FY2025
A4: Revenue | B4: 891311 | C4: 914472 | D4: 980136
A5: Net Profit | B5: 74088 | C5: 79020 | D5: 81309
B7: Chart 2:Profit Margins
B8: FY2023 | C8: FY2024 | D8: FY2025
A9: GP Margin % | B9: 33.97 | C9: 35.99 | D9: 35.75
A10: Net Profit Margin % | B10: 8.31 | C10: 8.64 | D10: 8.29
A11: EBITDA Margin % | B11: 17.27 | C11: 19.49 | D11: 16.88
B13: Chart 3:Liquidity Ratios
B14: FY2023 | C14: FY2024 | D14: FY2025
A15: Current Ratio | B15: 1.07 | C15: 1.18 | D15: 1.1
A16: Quick Ratio | B16: 0.72 | C16: 0.88 | D16: 0.84
B18: Chart 4:Debt to Equity
B19: FY2023 | C19: FY2024 | D19: FY2025
A20: Debt to Equity | B20: 0.38 | C20: 0.35 | D20: 0.34
B22: Chart 5:ROE vs ROA
B23: FY2023 | C23: FY2024 | D23: FY2025
A24: ROE % | B24: 8.94 | C24: 8.53 | D24: 8.05
A25: ROA % | B25: 4.61 | C25: 4.5 | D25: 4.17
J44: Chart 1: Revenue vs Net Profit | O44: Chart 4:Debt to Equity
J45: FY2023 | K45: FY2024 | L45: FY2025 | O45: FY2023 | P45: FY2024 | Q45: FY2025
I46: Revenue | J46: 891311 | K46: 914472 | L46: 980136 | N46: Debt to Equity | O46: 0.38 | P46: 0.35 | Q46: 0.34
I47: Net Profit | J47: 74088 | K47: 79020 | L47: 81309
J49: Chart 2:Profit Margins | O49: Chart 5:ROE vs ROA
J50: FY2023 | K50: FY2024 | L50: FY2025 | O50: FY2023 | P50: FY2024 | Q50: FY2025
I51: GP Margin % | J51: 33.97 | K51: 35.99 | L51: 35.75 | N51: ROE % | O51: 8.94 | P51: 8.53 | Q51: 8.05
I52: Net Profit Margin % | J52: 8.31 | K52: 8.64 | L52: 8.29 | N52: ROA % | O52: 4.61 | P52: 4.5 | Q52: 4.17
I53: EBITDA Margin % | J53: 17.27 | K53: 19.49 | L53: 16.88
J55: Chart 3:Liquidity Ratios
J56: FY2023 | K56: FY2024 | L56: FY2025
I57: Current Ratio | J57: 1.07 | K57: 1.18 | L57: 1.1
I58: Quick Ratio | J58: 0.72 | K58: 0.88 | L58: 0.84
